acm
config
