Metadata-Version: 1.0
Name: fc-config
Version: 0.1.5
Summary: fairsense config center sdk
Home-page: http://git.fairsense.cn
Author: wengyingjie
Author-email: yingjie.weng@fairsense.cn
License: Fairsense License 1.0
Platform: UNKNOWN
